{
  "data": {
    "article": {},
    "attachments": {
      "media_keys": [
        "3_1972836191759384576",
        "3_1972836193856552961",
        "3_1972836191998504960",
        "3_1972836191876833280"
      ]
    },
    "author_id": "1843201902550634496",
    "conversation_id": "1972836197493055586",
    "created_at": "2025-09-30T01:29:37.000Z",
    "edit_controls": {
      "editable_until": "2025-09-30T02:29:37.000Z",
      "edits_remaining": 5,
      "is_edit_eligible": true
    },
    "edit_history_tweet_ids": [
      "1972836197493055586"
    ],
    "entities": {
      "urls": [
        {
          "display_url": "pic.x.com/lBfVIS2ioG",
          "end": 47,
          "expanded_url": "https://x.com/LwrDHYyuxR22499/status/1972836197493055586/photo/1",
          "media_key": "3_1972836191759384576",
          "start": 24,
          "url": "https://t.co/lBfVIS2ioG"
        },
        {
          "display_url": "pic.x.com/lBfVIS2ioG",
          "end": 47,
          "expanded_url": "https://x.com/LwrDHYyuxR22499/status/1972836197493055586/photo/1",
          "media_key": "3_1972836193856552961",
          "start": 24,
          "url": "https://t.co/lBfVIS2ioG"
        },
        {
          "display_url": "pic.x.com/lBfVIS2ioG",
          "end": 47,
          "expanded_url": "https://x.com/LwrDHYyuxR22499/status/1972836197493055586/photo/1",
          "media_key": "3_1972836191998504960",
          "start": 24,
          "url": "https://t.co/lBfVIS2ioG"
        },
        {
          "display_url": "pic.x.com/lBfVIS2ioG",
          "end": 47,
          "expanded_url": "https://x.com/LwrDHYyuxR22499/status/1972836197493055586/photo/1",
          "media_key": "3_1972836191876833280",
          "start": 24,
          "url": "https://t.co/lBfVIS2ioG"
        }
      ]
    },
    "geo": {},
    "id": "1972836197493055586",
    "lang": "zh",
    "note_tweet": {
      "entities": {}
    },
    "possibly_sensitive": false,
    "public_metrics": {
      "bookmark_count": 0,
      "impression_count": 0,
      "like_count": 0,
      "quote_count": 0,
      "reply_count": 0,
      "retweet_count": 0
    },
    "reply_settings": "everyone",
    "text": "😪冷知识我其实比看起来要忙的多\n现在我要睡觉了 https://t.co/lBfVIS2ioG"
  },
  "includes": {
    "media": [
      {
        "height": 2048,
        "media_key": "3_1972836191759384576",
        "public_metrics": {},
        "type": "photo",
        "url": "https://pbs.twimg.com/media/G2DsEFnaQAATuEN.jpg",
        "width": 917
      },
      {
        "height": 1792,
        "media_key": "3_1972836193856552961",
        "public_metrics": {},
        "type": "photo",
        "url": "https://pbs.twimg.com/media/G2DsENbagAE_KDA.jpg",
        "width": 828
      },
      {
        "height": 2048,
        "media_key": "3_1972836191998504960",
        "public_metrics": {},
        "type": "photo",
        "url": "https://pbs.twimg.com/media/G2DsEGga8AAlx0q.jpg",
        "width": 917
      },
      {
        "height": 1792,
        "media_key": "3_1972836191876833280",
        "public_metrics": {},
        "type": "photo",
        "url": "https://pbs.twimg.com/media/G2DsEGDaYAAhm-n.jpg",
        "width": 828
      }
    ],
    "tweets": [
      {
        "article": {},
        "attachments": {
          "media_keys": [
            "3_1972836191759384576",
            "3_1972836193856552961",
            "3_1972836191998504960",
            "3_1972836191876833280"
          ]
        },
        "author_id": "1843201902550634496",
        "conversation_id": "1972836197493055586",
        "created_at": "2025-09-30T01:29:37.000Z",
        "edit_controls": {
          "editable_until": "2025-09-30T02:29:37.000Z",
          "edits_remaining": 5,
          "is_edit_eligible": true
        },
        "edit_history_tweet_ids": [
          "1972836197493055586"
        ],
        "entities": {
          "urls": [
            {
              "display_url": "pic.x.com/lBfVIS2ioG",
              "end": 47,
              "expanded_url": "https://x.com/LwrDHYyuxR22499/status/1972836197493055586/photo/1",
              "media_key": "3_1972836191759384576",
              "start": 24,
              "url": "https://t.co/lBfVIS2ioG"
            },
            {
              "display_url": "pic.x.com/lBfVIS2ioG",
              "end": 47,
              "expanded_url": "https://x.com/LwrDHYyuxR22499/status/1972836197493055586/photo/1",
              "media_key": "3_1972836193856552961",
              "start": 24,
              "url": "https://t.co/lBfVIS2ioG"
            },
            {
              "display_url": "pic.x.com/lBfVIS2ioG",
              "end": 47,
              "expanded_url": "https://x.com/LwrDHYyuxR22499/status/1972836197493055586/photo/1",
              "media_key": "3_1972836191998504960",
              "start": 24,
              "url": "https://t.co/lBfVIS2ioG"
            },
            {
              "display_url": "pic.x.com/lBfVIS2ioG",
              "end": 47,
              "expanded_url": "https://x.com/LwrDHYyuxR22499/status/1972836197493055586/photo/1",
              "media_key": "3_1972836191876833280",
              "start": 24,
              "url": "https://t.co/lBfVIS2ioG"
            }
          ]
        },
        "geo": {},
        "id": "1972836197493055586",
        "lang": "zh",
        "note_tweet": {
          "entities": {}
        },
        "possibly_sensitive": false,
        "public_metrics": {
          "bookmark_count": 0,
          "impression_count": 0,
          "like_count": 0,
          "quote_count": 0,
          "reply_count": 0,
          "retweet_count": 0
        },
        "reply_settings": "everyone",
        "text": "😪冷知识我其实比看起来要忙的多\n现在我要睡觉了 https://t.co/lBfVIS2ioG"
      }
    ],
    "users": [
      {
        "created_at": "2024-10-07T08:09:22.000Z",
        "description": "😃发表每日暴论还有更新生活日常所用墙内实名制上网\nChief Bastard- fucking officer\ncbo老祖cbo创始人欢迎入股",
        "id": "1843201902550634496",
        "name": "牧鸢",
        "pinned_tweet_id": "1924621705286496482",
        "profile_image_url": "https://pbs.twimg.com/profile_images/1945307289637785600/abykQYUN_normal.jpg",
        "protected": false,
        "public_metrics": {
          "followers_count": 837,
          "following_count": 776,
          "like_count": 644,
          "listed_count": 4,
          "media_count": 212,
          "tweet_count": 936
        },
        "username": "LwrDHYyuxR22499",
        "verified": false
      }
    ]
  }
}