{
  "data": {
    "article": {},
    "attachments": {
      "media_keys": [
        "3_1982617521950785536",
        "3_1982617522705776640",
        "3_1982617521913008128",
        "3_1982617523313930240"
      ]
    },
    "author_id": "1843201902550634496",
    "conversation_id": "1982617535603429410",
    "created_at": "2025-10-27T01:17:10.000Z",
    "edit_controls": {
      "editable_until": "2025-10-27T02:17:10.000Z",
      "edits_remaining": 5,
      "is_edit_eligible": true
    },
    "edit_history_tweet_ids": [
      "1982617535603429410"
    ],
    "entities": {
      "urls": [
        {
          "display_url": "pic.x.com/LrV6W7HVXC",
          "end": 37,
          "expanded_url": "https://x.com/LwrDHYyuxR22499/status/1982617535603429410/photo/1",
          "media_key": "3_1982617521950785536",
          "start": 14,
          "url": "https://t.co/LrV6W7HVXC"
        },
        {
          "display_url": "pic.x.com/LrV6W7HVXC",
          "end": 37,
          "expanded_url": "https://x.com/LwrDHYyuxR22499/status/1982617535603429410/photo/1",
          "media_key": "3_1982617522705776640",
          "start": 14,
          "url": "https://t.co/LrV6W7HVXC"
        },
        {
          "display_url": "pic.x.com/LrV6W7HVXC",
          "end": 37,
          "expanded_url": "https://x.com/LwrDHYyuxR22499/status/1982617535603429410/photo/1",
          "media_key": "3_1982617521913008128",
          "start": 14,
          "url": "https://t.co/LrV6W7HVXC"
        },
        {
          "display_url": "pic.x.com/LrV6W7HVXC",
          "end": 37,
          "expanded_url": "https://x.com/LwrDHYyuxR22499/status/1982617535603429410/photo/1",
          "media_key": "3_1982617523313930240",
          "start": 14,
          "url": "https://t.co/LrV6W7HVXC"
        }
      ]
    },
    "geo": {},
    "id": "1982617535603429410",
    "lang": "zh",
    "note_tweet": {
      "entities": {}
    },
    "possibly_sensitive": false,
    "public_metrics": {
      "bookmark_count": 0,
      "impression_count": 0,
      "like_count": 0,
      "quote_count": 0,
      "reply_count": 0,
      "retweet_count": 0
    },
    "reply_settings": "everyone",
    "text": "我醒来睁开眼要面对的事情🤓 https://t.co/LrV6W7HVXC"
  },
  "includes": {
    "media": [
      {
        "height": 1920,
        "media_key": "3_1982617521950785536",
        "public_metrics": {},
        "type": "photo",
        "url": "https://pbs.twimg.com/media/G4OsIcFXgAAp0Nh.jpg",
        "width": 860
      },
      {
        "height": 2048,
        "media_key": "3_1982617522705776640",
        "public_metrics": {},
        "type": "photo",
        "url": "https://pbs.twimg.com/media/G4OsIe5XwAA3jE-.jpg",
        "width": 917
      },
      {
        "height": 1920,
        "media_key": "3_1982617521913008128",
        "public_metrics": {},
        "type": "photo",
        "url": "https://pbs.twimg.com/media/G4OsIb8XEAAGnEk.jpg",
        "width": 1173
      },
      {
        "height": 1417,
        "media_key": "3_1982617523313930240",
        "public_metrics": {},
        "type": "photo",
        "url": "https://pbs.twimg.com/media/G4OsIhKXcAAuXiW.jpg",
        "width": 717
      }
    ],
    "tweets": [
      {
        "article": {},
        "attachments": {
          "media_keys": [
            "3_1982617521950785536",
            "3_1982617522705776640",
            "3_1982617521913008128",
            "3_1982617523313930240"
          ]
        },
        "author_id": "1843201902550634496",
        "conversation_id": "1982617535603429410",
        "created_at": "2025-10-27T01:17:10.000Z",
        "edit_controls": {
          "editable_until": "2025-10-27T02:17:10.000Z",
          "edits_remaining": 5,
          "is_edit_eligible": true
        },
        "edit_history_tweet_ids": [
          "1982617535603429410"
        ],
        "entities": {
          "urls": [
            {
              "display_url": "pic.x.com/LrV6W7HVXC",
              "end": 37,
              "expanded_url": "https://x.com/LwrDHYyuxR22499/status/1982617535603429410/photo/1",
              "media_key": "3_1982617521950785536",
              "start": 14,
              "url": "https://t.co/LrV6W7HVXC"
            },
            {
              "display_url": "pic.x.com/LrV6W7HVXC",
              "end": 37,
              "expanded_url": "https://x.com/LwrDHYyuxR22499/status/1982617535603429410/photo/1",
              "media_key": "3_1982617522705776640",
              "start": 14,
              "url": "https://t.co/LrV6W7HVXC"
            },
            {
              "display_url": "pic.x.com/LrV6W7HVXC",
              "end": 37,
              "expanded_url": "https://x.com/LwrDHYyuxR22499/status/1982617535603429410/photo/1",
              "media_key": "3_1982617521913008128",
              "start": 14,
              "url": "https://t.co/LrV6W7HVXC"
            },
            {
              "display_url": "pic.x.com/LrV6W7HVXC",
              "end": 37,
              "expanded_url": "https://x.com/LwrDHYyuxR22499/status/1982617535603429410/photo/1",
              "media_key": "3_1982617523313930240",
              "start": 14,
              "url": "https://t.co/LrV6W7HVXC"
            }
          ]
        },
        "geo": {},
        "id": "1982617535603429410",
        "lang": "zh",
        "note_tweet": {
          "entities": {}
        },
        "possibly_sensitive": false,
        "public_metrics": {
          "bookmark_count": 0,
          "impression_count": 0,
          "like_count": 0,
          "quote_count": 0,
          "reply_count": 0,
          "retweet_count": 0
        },
        "reply_settings": "everyone",
        "text": "我醒来睁开眼要面对的事情🤓 https://t.co/LrV6W7HVXC"
      }
    ],
    "users": [
      {
        "created_at": "2024-10-07T08:09:22.000Z",
        "description": "😃发表每日暴论还有更新生活日常所用墙内实名制上网\nChief Bastard- fucking officer\ncbo老祖cbo创始人欢迎入股",
        "id": "1843201902550634496",
        "name": "牧鸢",
        "pinned_tweet_id": "1973200474477306270",
        "profile_image_url": "https://pbs.twimg.com/profile_images/1945307289637785600/abykQYUN_normal.jpg",
        "protected": false,
        "public_metrics": {
          "followers_count": 1086,
          "following_count": 951,
          "like_count": 772,
          "listed_count": 5,
          "media_count": 257,
          "tweet_count": 1372
        },
        "username": "LwrDHYyuxR22499",
        "verified": false
      }
    ]
  }
}