{
  "data": {
    "article": {},
    "attachments": {},
    "author_id": "1843201902550634496",
    "conversation_id": "2068427392628949446",
    "created_at": "2026-06-20T21:17:20.000Z",
    "edit_controls": {
      "editable_until": "2026-06-20T22:17:20.000Z",
      "edits_remaining": 5,
      "is_edit_eligible": false
    },
    "edit_history_tweet_ids": [
      "2068443102550077822"
    ],
    "entities": {
      "mentions": [
        {
          "end": 13,
          "id": "1300828282061877249",
          "start": 0,
          "username": "HANLIANYI331"
        }
      ]
    },
    "geo": {},
    "id": "2068443102550077822",
    "in_reply_to_user_id": "1300828282061877249",
    "lang": "zh",
    "note_tweet": {
      "entities": {}
    },
    "possibly_sensitive": false,
    "public_metrics": {
      "bookmark_count": 0,
      "impression_count": 0,
      "like_count": 0,
      "quote_count": 0,
      "reply_count": 0,
      "retweet_count": 0
    },
    "referenced_tweets": [
      {
        "id": "2068442473496756568",
        "type": "replied_to"
      }
    ],
    "reply_settings": "everyone",
    "text": "@HANLIANYI331 小二对你的不实指控我有站出来反驳\n而我依旧保留我对你的指控"
  },
  "includes": {
    "tweets": [
      {
        "article": {},
        "attachments": {},
        "author_id": "1843201902550634496",
        "conversation_id": "2068427392628949446",
        "created_at": "2026-06-20T21:17:20.000Z",
        "edit_controls": {
          "editable_until": "2026-06-20T22:17:20.000Z",
          "edits_remaining": 5,
          "is_edit_eligible": false
        },
        "edit_history_tweet_ids": [
          "2068443102550077822"
        ],
        "entities": {
          "mentions": [
            {
              "end": 13,
              "id": "1300828282061877249",
              "start": 0,
              "username": "HANLIANYI331"
            }
          ]
        },
        "geo": {},
        "id": "2068443102550077822",
        "in_reply_to_user_id": "1300828282061877249",
        "lang": "zh",
        "note_tweet": {
          "entities": {}
        },
        "possibly_sensitive": false,
        "public_metrics": {
          "bookmark_count": 0,
          "impression_count": 0,
          "like_count": 0,
          "quote_count": 0,
          "reply_count": 0,
          "retweet_count": 0
        },
        "referenced_tweets": [
          {
            "id": "2068442473496756568",
            "type": "replied_to"
          }
        ],
        "reply_settings": "everyone",
        "text": "@HANLIANYI331 小二对你的不实指控我有站出来反驳\n而我依旧保留我对你的指控"
      },
      {
        "article": {},
        "attachments": {},
        "author_id": "1300828282061877249",
        "conversation_id": "2068427392628949446",
        "created_at": "2026-06-20T21:14:50.000Z",
        "edit_controls": {
          "editable_until": "2026-06-20T22:14:50.000Z",
          "edits_remaining": 5,
          "is_edit_eligible": false
        },
        "edit_history_tweet_ids": [
          "2068442473496756568"
        ],
        "entities": {
          "mentions": [
            {
              "end": 16,
              "id": "1843201902550634496",
              "start": 0,
              "username": "LwrDHYyuxR22499"
            }
          ],
          "urls": [
            {
              "display_url": "x.com/i/status/20003…",
              "end": 183,
              "expanded_url": "https://x.com/i/status/2000307397743837544",
              "start": 160,
              "url": "https://t.co/xvgZ7urkVn"
            }
          ]
        },
        "geo": {},
        "id": "2068442473496756568",
        "in_reply_to_user_id": "1843201902550634496",
        "lang": "zh",
        "note_tweet": {
          "entities": {
            "urls": [
              {
                "display_url": "x.com/i/status/20598…",
                "end": 279,
                "expanded_url": "https://x.com/i/status/2059801421500014971",
                "start": 256,
                "url": "https://t.co/0AdPnGB7cL"
              },
              {
                "display_url": "x.com/i/status/20003…",
                "end": 304,
                "expanded_url": "https://x.com/i/status/2000307397743837544",
                "start": 281,
                "url": "https://t.co/xvgZ7urkVn"
              }
            ]
          },
          "text": "你不能只在自己被造谣的时候谈论造谣的危害性，或者放任关于我的谣言的产生，谣言是可以被拼接的，哪怕是谈论伦理问题，不基于事发时的具体情景，只对“部分的事实”和“真空球形下的抽象行为本身”的讨论也同样可以被拼接。多年下来，我从未在任何人面前说过你的坏话或者放任过关于你的虚假指控（哪怕我明知道你曾经做过的大量争议性行为），因为你是少有的有在真正冒风险做实事的人。但是你非常不厚道的地方在于，你常常在你的社交圈子里放任关于我的谣言的流传，以及迟迟不和小二这类人的造谣行为（哪怕近两年你已经不再和对方合作）进行切割。\n\nhttps://t.co/0AdPnGB7cL\n\nhttps://t.co/xvgZ7urkVn"
        },
        "possibly_sensitive": false,
        "public_metrics": {
          "bookmark_count": 0,
          "impression_count": 10,
          "like_count": 0,
          "quote_count": 0,
          "reply_count": 1,
          "retweet_count": 0
        },
        "referenced_tweets": [
          {
            "id": "2000307397743837544",
            "type": "quoted"
          },
          {
            "id": "2068427392628949446",
            "type": "replied_to"
          }
        ],
        "reply_settings": "everyone",
        "text": "@LwrDHYyuxR22499 你不能只在自己被造谣的时候谈论造谣的危害性，或者放任关于我的谣言的产生，谣言是可以被拼接的，哪怕是谈论伦理问题，不基于事发时的具体情景，只对“部分的事实”和“真空球形下的抽象行为本身”的讨论也同样可以被拼接。多年下来，我从未在任何人面前说过你的坏话或者放任过关于你的虚假指控（哪怕我明 https://t.co/xvgZ7urkVn"
      }
    ],
    "users": [
      {
        "created_at": "2024-10-07T08:09:22.000Z",
        "description": "一名独立调查人，反扭转救援信息战主力、体系化反扭设计者，反邪教，反家暴\n曾受邀BBC Eye联合调查曝光违规机构，个案不定期登刊央视、东方卫视、中华网、半月谈以及各大新闻媒体。\n斩获2026年度新闻界🥇卓越奖\n最大的愿望是中国老百姓都能过上好日子",
        "id": "1843201902550634496",
        "name": "牧鸢",
        "pinned_tweet_id": "1999309621845254386",
        "profile_image_url": "https://pbs.twimg.com/profile_images/2067506601251205120/4q9AFRO7_normal.jpg",
        "protected": false,
        "public_metrics": {
          "followers_count": 5847,
          "following_count": 3195,
          "like_count": 3345,
          "listed_count": 18,
          "media_count": 464,
          "tweet_count": 3051
        },
        "url": "",
        "username": "LwrDHYyuxR22499",
        "verified": false
      },
      {
        "created_at": "2020-09-01T16:10:13.000Z",
        "description": "ASD｜ADHD｜如有危机干预信息请私信X账号@lianyiganyu｜咨询复杂问题可以向我预约时间付费咨询，如需联系我本人请私信telegram账号https://t.co/DPmfCokcD1｜因为消息繁多，如遇不回复消息的情况请重复向我发送信息｜我们活着就是对恶意最大的反抗",
        "entities": {
          "description": {
            "mentions": [
              {
                "end": 35,
                "start": 23,
                "username": "lianyiganyu"
              }
            ],
            "urls": [
              {
                "display_url": "t.me/HANLIANYI331",
                "end": 98,
                "expanded_url": "http://t.me/HANLIANYI331",
                "start": 75,
                "url": "https://t.co/DPmfCokcD1"
              }
            ]
          }
        },
        "id": "1300828282061877249",
        "location": "涟漪危机干预小组",
        "name": "寒涟漪",
        "pinned_tweet_id": "1883074968147431756",
        "profile_image_url": "https://pbs.twimg.com/profile_images/1701586146395127808/nXiZPlAl_normal.png",
        "protected": false,
        "public_metrics": {
          "followers_count": 41764,
          "following_count": 3826,
          "like_count": 1777,
          "listed_count": 2,
          "media_count": 399,
          "tweet_count": 2997
        },
        "url": "",
        "username": "HANLIANYI331",
        "verified": true
      }
    ]
  }
}