{
  "data": {
    "article": {},
    "attachments": {},
    "author_id": "1843201902550634496",
    "conversation_id": "2013635176920744045",
    "created_at": "2026-01-21T10:34:11.000Z",
    "edit_controls": {
      "editable_until": "2026-01-21T11:34:11.000Z",
      "edits_remaining": 5,
      "is_edit_eligible": false
    },
    "edit_history_tweet_ids": [
      "2013923072189911064"
    ],
    "entities": {
      "mentions": [
        {
          "end": 14,
          "id": "1558730611556175873",
          "start": 0,
          "username": "ChisakaKanako"
        },
        {
          "end": 23,
          "id": "961832160377282560",
          "start": 15,
          "username": "iMoeAya"
        }
      ]
    },
    "geo": {},
    "id": "2013923072189911064",
    "in_reply_to_user_id": "1558730611556175873",
    "lang": "zh",
    "note_tweet": {
      "entities": {}
    },
    "possibly_sensitive": false,
    "public_metrics": {
      "bookmark_count": 0,
      "impression_count": 0,
      "like_count": 0,
      "quote_count": 0,
      "reply_count": 0,
      "retweet_count": 0
    },
    "referenced_tweets": [
      {
        "id": "2013921978105967005",
        "type": "replied_to"
      }
    ],
    "reply_settings": "everyone",
    "text": "@ChisakaKanako @iMoeAya 啊，只能算是把人打了，但是他本来的任务是要保护跑到他那儿去的那个药娘的，但是那个药娘也被抓走了总的来说，任务还算是失败了。。"
  },
  "includes": {
    "tweets": [
      {
        "article": {},
        "attachments": {},
        "author_id": "1843201902550634496",
        "conversation_id": "2013635176920744045",
        "created_at": "2026-01-21T10:34:11.000Z",
        "edit_controls": {
          "editable_until": "2026-01-21T11:34:11.000Z",
          "edits_remaining": 5,
          "is_edit_eligible": false
        },
        "edit_history_tweet_ids": [
          "2013923072189911064"
        ],
        "entities": {
          "mentions": [
            {
              "end": 14,
              "id": "1558730611556175873",
              "start": 0,
              "username": "ChisakaKanako"
            },
            {
              "end": 23,
              "id": "961832160377282560",
              "start": 15,
              "username": "iMoeAya"
            }
          ]
        },
        "geo": {},
        "id": "2013923072189911064",
        "in_reply_to_user_id": "1558730611556175873",
        "lang": "zh",
        "note_tweet": {
          "entities": {}
        },
        "possibly_sensitive": false,
        "public_metrics": {
          "bookmark_count": 0,
          "impression_count": 0,
          "like_count": 0,
          "quote_count": 0,
          "reply_count": 0,
          "retweet_count": 0
        },
        "referenced_tweets": [
          {
            "id": "2013921978105967005",
            "type": "replied_to"
          }
        ],
        "reply_settings": "everyone",
        "text": "@ChisakaKanako @iMoeAya 啊，只能算是把人打了，但是他本来的任务是要保护跑到他那儿去的那个药娘的，但是那个药娘也被抓走了总的来说，任务还算是失败了。。"
      },
      {
        "article": {},
        "attachments": {},
        "author_id": "1558730611556175873",
        "conversation_id": "2013635176920744045",
        "created_at": "2026-01-21T10:29:51.000Z",
        "edit_controls": {
          "editable_until": "2026-01-21T11:29:51.000Z",
          "edits_remaining": 5,
          "is_edit_eligible": false
        },
        "edit_history_tweet_ids": [
          "2013921978105967005"
        ],
        "entities": {
          "mentions": [
            {
              "end": 16,
              "id": "1843201902550634496",
              "start": 0,
              "username": "LwrDHYyuxR22499"
            },
            {
              "end": 25,
              "id": "961832160377282560",
              "start": 17,
              "username": "iMoeAya"
            }
          ]
        },
        "geo": {},
        "id": "2013921978105967005",
        "in_reply_to_user_id": "1843201902550634496",
        "lang": "zh",
        "note_tweet": {
          "entities": {}
        },
        "possibly_sensitive": false,
        "public_metrics": {
          "bookmark_count": 0,
          "impression_count": 4,
          "like_count": 0,
          "quote_count": 0,
          "reply_count": 1,
          "retweet_count": 0
        },
        "referenced_tweets": [
          {
            "id": "2013822720635486562",
            "type": "replied_to"
          }
        ],
        "reply_settings": "everyone",
        "text": "@LwrDHYyuxR22499 @iMoeAya 命令方块（？"
      }
    ],
    "users": [
      {
        "created_at": "2024-10-07T08:09:22.000Z",
        "description": "一名独立调查人\n因个人能力突出\n曾受邀与BBC Eye对扭转机构进行曝光",
        "id": "1843201902550634496",
        "name": "牧鸢",
        "pinned_tweet_id": "1973200474477306270",
        "profile_image_url": "https://pbs.twimg.com/profile_images/2011452921763000321/hR0Dmp8c_normal.jpg",
        "protected": false,
        "public_metrics": {
          "followers_count": 2597,
          "following_count": 1633,
          "like_count": 1383,
          "listed_count": 10,
          "media_count": 315,
          "tweet_count": 1934
        },
        "username": "LwrDHYyuxR22499",
        "verified": false
      },
      {
        "created_at": "2022-08-14T08:22:12.000Z",
        "description": "🧁 2026",
        "entities": {
          "url": {
            "urls": [
              {
                "display_url": "bento.me/chisakakanako",
                "end": 23,
                "expanded_url": "http://bento.me/chisakakanako",
                "start": 0,
                "url": "https://t.co/gu1Hf8BDRc"
              }
            ]
          }
        },
        "id": "1558730611556175873",
        "location": "大连",
        "name": "千坂神奈子",
        "pinned_tweet_id": "1971608331635818577",
        "profile_image_url": "https://pbs.twimg.com/profile_images/2005160042845405188/7FNnSndN_normal.jpg",
        "protected": false,
        "public_metrics": {
          "followers_count": 5989,
          "following_count": 1578,
          "like_count": 43133,
          "listed_count": 10,
          "media_count": 79,
          "tweet_count": 647
        },
        "url": "https://t.co/gu1Hf8BDRc",
        "username": "ChisakaKanako",
        "verified": false
      },
      {
        "created_at": "2018-02-09T05:20:31.000Z",
        "description": "MTF/神楽坂/m属性⛓️/被B不恼/硬件DIY/玄学党🎧/响酱赛高💖/有主人📝 /Ingress🌱/风景摄影📷 /coser/🏳️‍🌈/G+难民/开发5cm/纯个人向分享推/不卖货🙅🏻‍♀️想要拍出可爱撩人的照片～喜欢请点个♥吧～萌绫会很开心的✧٩(ˊωˋ*)و\n无任何小号,所有自称小号都是冒充",
        "entities": {
          "url": {
            "urls": [
              {
                "display_url": "t.me/MoeAya",
                "end": 23,
                "expanded_url": "https://t.me/MoeAya",
                "start": 0,
                "url": "https://t.co/3v3qwKUA0k"
              }
            ]
          }
        },
        "id": "961832160377282560",
        "location": "新宿 神楽坂",
        "name": "神楽坂 萌绫🏳️‍⚧️",
        "pinned_tweet_id": "1913122531071975435",
        "profile_image_url": "https://pbs.twimg.com/profile_images/1974770448509595648/kkt3Z048_normal.jpg",
        "protected": false,
        "public_metrics": {
          "followers_count": 40363,
          "following_count": 4816,
          "like_count": 174841,
          "listed_count": 145,
          "media_count": 1153,
          "tweet_count": 35433
        },
        "url": "https://t.co/3v3qwKUA0k",
        "username": "iMoeAya",
        "verified": false
      }
    ]
  }
}