{
  "data": {
    "article": {},
    "attachments": {},
    "author_id": "1843201902550634496",
    "conversation_id": "2026550301348737112",
    "created_at": "2026-02-26T03:37:07.000Z",
    "edit_controls": {
      "editable_until": "2026-02-26T04:37:07.000Z",
      "edits_remaining": 5,
      "is_edit_eligible": false
    },
    "edit_history_tweet_ids": [
      "2026864075343540282"
    ],
    "entities": {
      "mentions": [
        {
          "end": 16,
          "id": "1932608318364942336",
          "start": 0,
          "username": "CatzillainChina"
        },
        {
          "end": 33,
          "id": "2016022863174852609",
          "start": 17,
          "username": "hamster_pro_max"
        }
      ]
    },
    "geo": {},
    "id": "2026864075343540282",
    "in_reply_to_user_id": "1932608318364942336",
    "lang": "zh",
    "note_tweet": {
      "entities": {}
    },
    "possibly_sensitive": false,
    "public_metrics": {
      "bookmark_count": 0,
      "impression_count": 0,
      "like_count": 0,
      "quote_count": 0,
      "reply_count": 0,
      "retweet_count": 0
    },
    "referenced_tweets": [
      {
        "id": "2026651133587124575",
        "type": "replied_to"
      }
    ],
    "reply_settings": "everyone",
    "text": "@CatzillainChina @hamster_pro_max 这不巧了我组员这边也有救猫反虐猫蛆的😁"
  },
  "includes": {
    "tweets": [
      {
        "article": {},
        "attachments": {},
        "author_id": "1843201902550634496",
        "conversation_id": "2026550301348737112",
        "created_at": "2026-02-26T03:37:07.000Z",
        "edit_controls": {
          "editable_until": "2026-02-26T04:37:07.000Z",
          "edits_remaining": 5,
          "is_edit_eligible": false
        },
        "edit_history_tweet_ids": [
          "2026864075343540282"
        ],
        "entities": {
          "mentions": [
            {
              "end": 16,
              "id": "1932608318364942336",
              "start": 0,
              "username": "CatzillainChina"
            },
            {
              "end": 33,
              "id": "2016022863174852609",
              "start": 17,
              "username": "hamster_pro_max"
            }
          ]
        },
        "geo": {},
        "id": "2026864075343540282",
        "in_reply_to_user_id": "1932608318364942336",
        "lang": "zh",
        "note_tweet": {
          "entities": {}
        },
        "possibly_sensitive": false,
        "public_metrics": {
          "bookmark_count": 0,
          "impression_count": 0,
          "like_count": 0,
          "quote_count": 0,
          "reply_count": 0,
          "retweet_count": 0
        },
        "referenced_tweets": [
          {
            "id": "2026651133587124575",
            "type": "replied_to"
          }
        ],
        "reply_settings": "everyone",
        "text": "@CatzillainChina @hamster_pro_max 这不巧了我组员这边也有救猫反虐猫蛆的😁"
      },
      {
        "article": {},
        "attachments": {},
        "author_id": "1932608318364942336",
        "conversation_id": "2026550301348737112",
        "created_at": "2026-02-25T13:30:58.000Z",
        "edit_controls": {
          "editable_until": "2026-02-25T14:30:58.000Z",
          "edits_remaining": 5,
          "is_edit_eligible": false
        },
        "edit_history_tweet_ids": [
          "2026651133587124575"
        ],
        "entities": {
          "mentions": [
            {
              "end": 16,
              "id": "1843201902550634496",
              "start": 0,
              "username": "LwrDHYyuxR22499"
            },
            {
              "end": 33,
              "id": "2016022863174852609",
              "start": 17,
              "username": "hamster_pro_max"
            }
          ]
        },
        "geo": {},
        "id": "2026651133587124575",
        "in_reply_to_user_id": "1843201902550634496",
        "lang": "zh",
        "note_tweet": {
          "entities": {}
        },
        "possibly_sensitive": false,
        "public_metrics": {
          "bookmark_count": 1,
          "impression_count": 657,
          "like_count": 0,
          "quote_count": 0,
          "reply_count": 0,
          "retweet_count": 0
        },
        "referenced_tweets": [
          {
            "id": "2026592715639763325",
            "type": "replied_to"
          }
        ],
        "reply_settings": "everyone",
        "text": "@LwrDHYyuxR22499 @hamster_pro_max 的确，救猫是如此，救人也是一样。我们救的猫找回主人后让主人报个案都不肯的一大把。"
      }
    ],
    "users": [
      {
        "created_at": "2024-10-07T08:09:22.000Z",
        "description": "一名独立调查人\n因个人能力突出\n曾受邀与BBC Eye对扭转机构进行曝光",
        "id": "1843201902550634496",
        "name": "牧鸢",
        "pinned_tweet_id": "1973200474477306270",
        "profile_image_url": "https://pbs.twimg.com/profile_images/2011452921763000321/hR0Dmp8c_normal.jpg",
        "protected": false,
        "public_metrics": {
          "followers_count": 3325,
          "following_count": 1917,
          "like_count": 1788,
          "listed_count": 12,
          "media_count": 344,
          "tweet_count": 2241
        },
        "username": "LwrDHYyuxR22499",
        "verified": false
      },
      {
        "created_at": "2025-06-11T01:18:38.000Z",
        "description": "我们是一群生活在中国的普通人，却走在打击偷猫黑色产业链的最前线。从追踪偷猫贼，到拦截非法运输的「猫车」，再到揭露屠宰点和黑产网络，我们用镜头记录每一场行动、每一次救援、每一只生命挣扎的瞬间。",
        "entities": {
          "url": {
            "urls": [
              {
                "display_url": "youtube.com/channel/UCFEPz…",
                "end": 23,
                "expanded_url": "https://youtube.com/channel/UCFEPzMWHtQwGN5yg559gRrw?si=oQtGDBAsDOXKRVlE",
                "start": 0,
                "url": "https://t.co/A6u1UXFws5"
              }
            ]
          }
        },
        "id": "1932608318364942336",
        "name": "穿靴子的猫Catzilla",
        "profile_image_url": "https://pbs.twimg.com/profile_images/1932609104888922112/TxVLLuRK_normal.jpg",
        "protected": false,
        "public_metrics": {
          "followers_count": 1,
          "following_count": 7,
          "like_count": 12,
          "listed_count": 0,
          "media_count": 4,
          "tweet_count": 37
        },
        "url": "https://t.co/A6u1UXFws5",
        "username": "CatzillainChina",
        "verified": false
      },
      {
        "created_at": "2026-01-27T05:38:10.000Z",
        "description": "第一次玩推，第一个推特账号，终于找到大部队了（以前只玩贴吧知乎b站之类的，别问我为啥知道很多圈内事，我只是刚注册推特账号，不代表我断了网了🥹😇）/HRT 2024.1月mtf，攒钱手术中/分享碎碎念和我的生活！可以同类互fo交友哦（纯绿）",
        "id": "2016022863174852609",
        "location": "距离您十万八千里",
        "name": "囤囤鼠🍥",
        "pinned_tweet_id": "2023380080551207253",
        "profile_image_url": "https://pbs.twimg.com/profile_images/2016057442216669184/Oi8cR-nj_normal.jpg",
        "protected": false,
        "public_metrics": {
          "followers_count": 48,
          "following_count": 111,
          "like_count": 454,
          "listed_count": 0,
          "media_count": 4,
          "tweet_count": 60
        },
        "username": "hamster_pro_max",
        "verified": false
      }
    ]
  }
}