{
  "data": {
    "article": {},
    "attachments": {},
    "author_id": "1843201902550634496",
    "conversation_id": "2039058807305933277",
    "created_at": "2026-03-31T19:23:57.000Z",
    "edit_controls": {
      "editable_until": "2026-03-31T20:23:57.000Z",
      "edits_remaining": 5,
      "is_edit_eligible": false
    },
    "edit_history_tweet_ids": [
      "2039061153423466542"
    ],
    "entities": {
      "mentions": [
        {
          "end": 16,
          "id": "1991445096013918208",
          "start": 0,
          "username": "SakurabaEma_ITN"
        },
        {
          "end": 26,
          "id": "1768309380108406784",
          "start": 17,
          "username": "abaablon"
        }
      ]
    },
    "geo": {},
    "id": "2039061153423466542",
    "in_reply_to_user_id": "1991445096013918208",
    "lang": "zh",
    "note_tweet": {
      "entities": {}
    },
    "possibly_sensitive": false,
    "public_metrics": {
      "bookmark_count": 0,
      "impression_count": 0,
      "like_count": 0,
      "quote_count": 0,
      "reply_count": 0,
      "retweet_count": 0
    },
    "referenced_tweets": [
      {
        "id": "2039060964583301477",
        "type": "replied_to"
      }
    ],
    "reply_settings": "everyone",
    "text": "@SakurabaEma_ITN @abaablon 对不起扭转机构还没对我们做过这么恶俗的事情"
  },
  "includes": {
    "tweets": [
      {
        "article": {},
        "attachments": {},
        "author_id": "1843201902550634496",
        "conversation_id": "2039058807305933277",
        "created_at": "2026-03-31T19:23:57.000Z",
        "edit_controls": {
          "editable_until": "2026-03-31T20:23:57.000Z",
          "edits_remaining": 5,
          "is_edit_eligible": false
        },
        "edit_history_tweet_ids": [
          "2039061153423466542"
        ],
        "entities": {
          "mentions": [
            {
              "end": 16,
              "id": "1991445096013918208",
              "start": 0,
              "username": "SakurabaEma_ITN"
            },
            {
              "end": 26,
              "id": "1768309380108406784",
              "start": 17,
              "username": "abaablon"
            }
          ]
        },
        "geo": {},
        "id": "2039061153423466542",
        "in_reply_to_user_id": "1991445096013918208",
        "lang": "zh",
        "note_tweet": {
          "entities": {}
        },
        "possibly_sensitive": false,
        "public_metrics": {
          "bookmark_count": 0,
          "impression_count": 0,
          "like_count": 0,
          "quote_count": 0,
          "reply_count": 0,
          "retweet_count": 0
        },
        "referenced_tweets": [
          {
            "id": "2039060964583301477",
            "type": "replied_to"
          }
        ],
        "reply_settings": "everyone",
        "text": "@SakurabaEma_ITN @abaablon 对不起扭转机构还没对我们做过这么恶俗的事情"
      },
      {
        "article": {},
        "attachments": {},
        "author_id": "1991445096013918208",
        "conversation_id": "2039058807305933277",
        "created_at": "2026-03-31T19:23:12.000Z",
        "edit_controls": {
          "editable_until": "2026-03-31T20:23:12.000Z",
          "edits_remaining": 5,
          "is_edit_eligible": false
        },
        "edit_history_tweet_ids": [
          "2039060964583301477"
        ],
        "entities": {
          "mentions": [
            {
              "end": 9,
              "id": "1768309380108406784",
              "start": 0,
              "username": "abaablon"
            },
            {
              "end": 26,
              "id": "1843201902550634496",
              "start": 10,
              "username": "LwrDHYyuxR22499"
            }
          ]
        },
        "geo": {},
        "id": "2039060964583301477",
        "in_reply_to_user_id": "1768309380108406784",
        "lang": "zh",
        "note_tweet": {
          "entities": {}
        },
        "possibly_sensitive": false,
        "public_metrics": {
          "bookmark_count": 0,
          "impression_count": 5,
          "like_count": 0,
          "quote_count": 0,
          "reply_count": 1,
          "retweet_count": 1
        },
        "referenced_tweets": [
          {
            "id": "2039060744357244984",
            "type": "replied_to"
          }
        ],
        "reply_settings": "everyone",
        "text": "@abaablon @LwrDHYyuxR22499 是的，如果只怀疑是社群里的人干的\n那就有有意引导的嫌疑了\n……"
      }
    ],
    "users": [
      {
        "created_at": "2024-10-07T08:09:22.000Z",
        "description": "一名独立调查人\n因个人能力突出\n曾受邀与BBC Eye对扭转机构进行曝光",
        "id": "1843201902550634496",
        "name": "牧鸢",
        "pinned_tweet_id": "1999309621845254386",
        "profile_image_url": "https://pbs.twimg.com/profile_images/2033978135059062784/y7sj8Gmi_normal.jpg",
        "protected": false,
        "public_metrics": {
          "followers_count": 4000,
          "following_count": 2329,
          "like_count": 2365,
          "listed_count": 15,
          "media_count": 383,
          "tweet_count": 2541
        },
        "username": "LwrDHYyuxR22499",
        "verified": false
      },
      {
        "created_at": "2025-11-20T09:54:50.000Z",
        "description": "｜真理不靠雷霆落，破尽谎言路自开｜以是非定立场而不是以立场定是非｜主人老婆 @KOISHI_IV｜“我希望有一天，所有人都能站在自由民主平等的蓝天之下”｜",
        "entities": {
          "description": {
            "mentions": [
              {
                "end": 48,
                "start": 38,
                "username": "KOISHI_IV"
              }
            ]
          },
          "url": {
            "urls": [
              {
                "display_url": "ngl.link/sakurabaema_itn",
                "end": 23,
                "expanded_url": "https://ngl.link/sakurabaema_itn",
                "start": 0,
                "url": "https://t.co/nTmMgey0m1"
              }
            ]
          }
        },
        "id": "1991445096013918208",
        "location": "马斯克的祖坟头上",
        "name": "英酱猫猫🍥",
        "pinned_tweet_id": "2021286628187320504",
        "profile_image_url": "https://pbs.twimg.com/profile_images/1991445156823003136/fQqmo6Tk_normal.jpg",
        "protected": false,
        "public_metrics": {
          "followers_count": 531,
          "following_count": 94,
          "like_count": 4022,
          "listed_count": 0,
          "media_count": 76,
          "tweet_count": 707
        },
        "url": "https://t.co/nTmMgey0m1",
        "username": "SakurabaEma_ITN",
        "verified": false
      },
      {
        "created_at": "2024-03-14T16:13:15.000Z",
        "description": "❤️平等 科学 自由 平和 友愛☀️\n激进(顺)男(同)权\n「インセストサポーター」\nちち@SShn_30741 はは@kir1same7",
        "entities": {
          "description": {
            "mentions": [
              {
                "end": 56,
                "start": 45,
                "username": "SShn_30741"
              },
              {
                "end": 69,
                "start": 59,
                "username": "kir1same7"
              }
            ]
          }
        },
        "id": "1768309380108406784",
        "location": "kuishuu",
        "name": "Abaablon🏳️‍🌈🏳️‍⚧️",
        "pinned_tweet_id": "1981677439614087425",
        "profile_image_url": "https://pbs.twimg.com/profile_images/2002788092428836865/obEOgkd4_normal.jpg",
        "protected": false,
        "public_metrics": {
          "followers_count": 502,
          "following_count": 393,
          "like_count": 28345,
          "listed_count": 2,
          "media_count": 62,
          "tweet_count": 1743
        },
        "username": "abaablon",
        "verified": false
      }
    ]
  }
}